{
  "volume": 2,
  "page_index": 111,
  "pdf_page": 112,
  "lines": [
    {
      "text": "135",
      "box": [
        17,
        81,
        59,
        108
      ],
      "score": 0.9999508857727051
    },
    {
      "text": "IV. REYES:",
      "box": [
        244,
        89,
        366,
        118
      ],
      "score": 0.9620741009712219
    },
    {
      "text": "CAPITULO IV.",
      "box": [
        978,
        81,
        1131,
        105
      ],
      "score": 0.9994332194328308
    },
    {
      "text": "136",
      "box": [
        1273,
        95,
        1306,
        120
      ],
      "score": 0.9999905228614807
    },
    {
      "text": "19. Y destruireis todas las plazas fuertes, y todas las ciu-",
      "box": [
        29,
        149,
        600,
        194
      ],
      "score": 0.9997016787528992
    },
    {
      "text": "10. Dispongamos pues para él un cuartito, y pongamos en",
      "box": [
        774,
        144,
        1320,
        186
      ],
      "score": 0.9938660264015198
    },
    {
      "text": "dades principales, y cortareis todos los árboles frutales, y",
      "box": [
        8,
        176,
        601,
        218
      ],
      "score": 0.9989560842514038
    },
    {
      "text": "él una cama, y una mesa, y una silla, y un candelero, para que",
      "box": [
        754,
        171,
        1319,
        212
      ],
      "score": 0.9451733231544495
    },
    {
      "text": "cegareis todos los manantiales de aguas, y sembrareis de pie-",
      "box": [
        8,
        205,
        601,
        242
      ],
      "score": 0.9853855967521667
    },
    {
      "text": "cuando viniere á nuestra casa, se recoja en él.",
      "box": [
        757,
        201,
        1187,
        232
      ],
      "score": 0.9994204640388489
    },
    {
      "text": "dras todos los campos mas fértiles.",
      "box": [
        10,
        232,
        348,
        261
      ],
      "score": 0.9910210967063904
    },
    {
      "text": "11. En efecto, habiendo llegado cierto dia, se aposentó en",
      "box": [
        777,
        227,
        1317,
        257
      ],
      "score": 0.9834405779838562
    },
    {
      "text": "20. Con efecto, llegada la mañana, al tiempo que suele",
      "box": [
        34,
        258,
        601,
        291
      ],
      "score": 0.9938823580741882
    },
    {
      "text": "este cuartito, y allí reposó.",
      "box": [
        757,
        252,
        1006,
        280
      ],
      "score": 0.9864513874053955
    },
    {
      "text": "ofrecerse el sacrificio, ya las aguas venian corriendo por el ca-",
      "box": [
        13,
        283,
        601,
        316
      ],
      "score": 0.9944696426391602
    },
    {
      "text": "12. Y dijo á su criado Giezi: Llama á esa Sunamitis. Lla-",
      "box": [
        777,
        277,
        1318,
        305
      ],
      "score": 0.9913231730461121
    },
    {
      "text": "mino de Edom; é inundóse de agua todo aquel terreno.",
      "box": [
        14,
        309,
        536,
        338
      ],
      "score": 0.9975001215934753
    },
    {
      "text": "móla Giezi; y ella se presentó ⁶ á Eliséo:",
      "box": [
        757,
        303,
        1134,
        330
      ],
      "score": 0.96644526720047
    },
    {
      "text": "21. Al mismo tiempo los Moabitas, todos á una, oyendo que",
      "box": [
        37,
        332,
        600,
        364
      ],
      "score": 0.9872257709503174
    },
    {
      "text": "13. El cual dijo á su criado: Díle de mi parte: Veò que nos",
      "box": [
        778,
        329,
        1318,
        354
      ],
      "score": 0.9735705852508545
    },
    {
      "text": "aquellos reyes habian salido á campaña contra ellos, convoca-",
      "box": [
        14,
        358,
        601,
        388
      ],
      "score": 0.9997829794883728
    },
    {
      "text": "has asistido en todo con mucho esmero. ¿Qué quieres que haga",
      "box": [
        756,
        353,
        1318,
        380
      ],
      "score": 0.9904166460037231
    },
    {
      "text": "ron á todos los hombres aptos para la guerra, y vinieron á es-",
      "box": [
        13,
        381,
        599,
        412
      ],
      "score": 0.9877684712409973
    },
    {
      "text": "por tí? ¿Tienes algun negocio, sobre el cual pueda yo hablar al",
      "box": [
        756,
        376,
        1319,
        406
      ],
      "score": 0.9818035960197449
    },
    {
      "text": "perarlos en las fronteras.",
      "box": [
        13,
        406,
        258,
        437
      ],
      "score": 0.9999784231185913
    },
    {
      "text": "rey ó al general del ejército? Respondió ella: Yo vivo feliz-",
      "box": [
        755,
        400,
        1318,
        430
      ],
      "score": 0.9887121319770813
    },
    {
      "text": "22. Y habiéndose levantado al apuntar el dia, luego que",
      "box": [
        36,
        430,
        597,
        459
      ],
      "score": 0.997402548789978
    },
    {
      "text": "mente en medio de mis gentes.",
      "box": [
        755,
        428,
        1047,
        454
      ],
      "score": 0.9848071336746216
    },
    {
      "text": "los rayos del sol brillaron sobre las aguas, les parecieron estas",
      "box": [
        13,
        454,
        598,
        482
      ],
      "score": 0.991851806640625
    },
    {
      "text": "14. ¿Qué quiere pues, replicó Eliséo, que haga yo por ella?",
      "box": [
        775,
        446,
        1320,
        480
      ],
      "score": 0.9955934286117554
    },
    {
      "text": "rojas como sangre.",
      "box": [
        15,
        480,
        201,
        506
      ],
      "score": 0.9999047517776489
    },
    {
      "text": "Respondió Giezi: No hay que preguntárselo, supuesto que no",
      "box": [
        753,
        471,
        1319,
        504
      ],
      "score": 0.9981607794761658
    },
    {
      "text": "23. Por lo cual dijeron: Sangre de batalla es: los reyes han",
      "box": [
        38,
        502,
        597,
        529
      ],
      "score": 0.9920756816864014
    },
    {
      "text": "tiene hijos, y que su marido es ya viejo.",
      "box": [
        754,
        499,
        1125,
        528
      ],
      "score": 0.99552321434021
    },
    {
      "text": "peleado contra sí, y se han acuchillado unos á otros: corre",
      "box": [
        14,
        524,
        597,
        554
      ],
      "score": 0.9830326437950134
    },
    {
      "text": "15. En consecuencia mandó que la llamase otra vez, y",
      "box": [
        773,
        519,
        1320,
        554
      ],
      "score": 0.9919961094856262
    },
    {
      "text": "ahora, oh Moab, á recoger la presa.",
      "box": [
        15,
        550,
        353,
        580
      ],
      "score": 0.9930070042610168
    },
    {
      "text": "venido que hubo, y parándose ante la puerta por respeto al",
      "box": [
        751,
        541,
        1321,
        581
      ],
      "score": 0.9987730383872986
    },
    {
      "text": "24. En efecto corrieron al campamento de Israél: mas los",
      "box": [
        36,
        572,
        597,
        603
      ],
      "score": 0.9918755292892456
    },
    {
      "text": "Profeta,",
      "box": [
        752,
        576,
        833,
        604
      ],
      "score": 0.971477746963501
    },
    {
      "text": "Israelitas, puestos sobre las armas, dieron contra los Moabitas,",
      "box": [
        14,
        599,
        596,
        627
      ],
      "score": 0.9997702240943909
    },
    {
      "text": "16. Le dijo Eliséo: El año que viene, en este tiempo y en",
      "box": [
        772,
        591,
        1319,
        631
      ],
      "score": 0.9964251518249512
    },
    {
      "text": "y los pusieron en fuga. Con esto fueron tras ellos los vencedo-",
      "box": [
        13,
        624,
        598,
        653
      ],
      "score": 0.9985660910606384
    },
    {
      "text": "esta misma hora, dándote Dios vida, llevarás un hijo en tús",
      "box": [
        752,
        614,
        1319,
        657
      ],
      "score": 0.9764783978462219
    },
    {
      "text": "res, y destrozaron á Moab,",
      "box": [
        16,
        652,
        273,
        675
      ],
      "score": 0.9886566400527954
    },
    {
      "text": "entrañas. A lo que respondió ella: No quieras, señor mio,",
      "box": [
        750,
        638,
        1320,
        682
      ],
      "score": 0.9997678995132446
    },
    {
      "text": "25. Destruyeron sus ciudades, llenaron de piedras, que",
      "box": [
        40,
        673,
        596,
        697
      ],
      "score": 0.9961764216423035
    },
    {
      "text": "no quieras por tu vida, oh varon de Dios, engañar á tu",
      "box": [
        750,
        661,
        1320,
        707
      ],
      "score": 0.9928215742111206
    },
    {
      "text": "cada uno echaba, los campos mas fértiles, cegaron todos los",
      "box": [
        18,
        698,
        597,
        722
      ],
      "score": 0.986417293548584
    },
    {
      "text": "sierva.",
      "box": [
        752,
        700,
        819,
        725
      ],
      "score": 0.9991968870162964
    },
    {
      "text": "manantiales de las aguas, y cortaron todos los árboles frutales;",
      "box": [
        16,
        721,
        598,
        746
      ],
      "score": 0.9996284246444702
    },
    {
      "text": "17. Mas en efecto, la mujer concibió, y parió un hijo al",
      "box": [
        771,
        709,
        1320,
        754
      ],
      "score": 0.9908307790756226
    },
    {
      "text": "de suerte que solamente quedaron los muròs de ladrillo óel",
      "box": [
        16,
        743,
        600,
        773
      ],
      "score": 0.9932692050933838
    },
    {
      "text": "tiempo y á la hora misma señalada por Eliséo.",
      "box": [
        753,
        741,
        1179,
        777
      ],
      "score": 0.9957020878791809
    },
    {
      "text": "castillo; mas la ciudad fué cercada por los honderos ¹, y en",
      "box": [
        16,
        769,
        598,
        796
      ],
      "score": 0.9742006063461304
    },
    {
      "text": "18. El niño fué creciendo; y habiendo sálido un dia para ir",
      "box": [
        772,
        757,
        1320,
        805
      ],
      "score": 0.9876214265823364
    },
    {
      "text": "gran parte derribada.",
      "box": [
        16,
        796,
        229,
        823
      ],
      "score": 0.999975860118866
    },
    {
      "text": "á encontrar á su padre, que estaba con los segadores,",
      "box": [
        753,
        788,
        1241,
        829
      ],
      "score": 0.9973261952400208
    },
    {
      "text": "26. Habiendo visto pues el rey de Moab que los enemigos",
      "box": [
        40,
        819,
        598,
        845
      ],
      "score": 0.9895012378692627
    },
    {
      "text": "19. Dijo á su padre: La cabeza me duele, me duele la",
      "box": [
        768,
        804,
        1320,
        857
      ],
      "score": 0.9991869330406189
    },
    {
      "text": "prevalecian, tomó consigo setecientos hombres valerosos con",
      "box": [
        15,
        842,
        600,
        873
      ],
      "score": 0.9995386004447937
    },
    {
      "text": "cabeza. Dijo el padre á un criado: Tómale y llévale á su",
      "box": [
        751,
        828,
        1320,
        882
      ],
      "score": 0.9868202805519104
    },
    {
      "text": "espada en mano, para forzar el campo del rey de Iduméa, y",
      "box": [
        16,
        868,
        601,
        897
      ],
      "score": 0.9993696212768555
    },
    {
      "text": "madre.",
      "box": [
        755,
        877,
        824,
        899
      ],
      "score": 0.9999933242797852
    },
    {
      "text": "escaparse; pero no pudo lograr su intento.",
      "box": [
        17,
        893,
        420,
        921
      ],
      "score": 0.9951437711715698
    },
    {
      "text": "20. Habiéndole éste cogido y llevado á su madre, le tuvo",
      "box": [
        773,
        876,
        1319,
        928
      ],
      "score": 0.9908686876296997
    },
    {
      "text": "27. Y arrebatando á su hijo primogénito, que debia suce-",
      "box": [
        39,
        915,
        601,
        945
      ],
      "score": 0.99892657995224
    },
    {
      "text": "ella sobre sus rodillas hasta el medio dia, en que murió.",
      "box": [
        753,
        902,
        1266,
        953
      ],
      "score": 0.9995636940002441
    },
    {
      "text": "derle en el reino, ofrecióle en holocausto ² sobre la muralla:",
      "box": [
        18,
        941,
        601,
        970
      ],
      "score": 0.9932664632797241
    },
    {
      "text": "21. Subió luego arriba, y púsole sobre la cama del varon",
      "box": [
        774,
        924,
        1319,
        978
      ],
      "score": 0.994416356086731
    },
    {
      "text": "cosa que causó grande horror á los Israelitas;y así al punto se",
      "box": [
        17,
        965,
        602,
        998
      ],
      "score": 0.9997391700744629
    },
    {
      "text": "de Dios, y cerróla puerta; y habiendo salido,",
      "box": [
        756,
        958,
        1168,
        998
      ],
      "score": 0.9888768792152405
    },
    {
      "text": "retiraron de allí, volviendo á sus casas.",
      "box": [
        17,
        995,
        394,
        1022
      ],
      "score": 0.9804369211196899
    },
    {
      "text": "22. Llamó á su marido, á quien dijo: Despacha conmigo, te",
      "box": [
        774,
        972,
        1320,
        1025
      ],
      "score": 0.987399160861969
    },
    {
      "text": "ruego, alguno de los criados y una borrica, para ir yo corrien-",
      "box": [
        753,
        997,
        1320,
        1050
      ],
      "score": 0.999699056148529
    },
    {
      "text": "CAPITULO IV",
      "box": [
        248,
        1038,
        391,
        1066
      ],
      "score": 0.9994643926620483
    },
    {
      "text": "do al varon de Dios y volver luego.",
      "box": [
        757,
        1037,
        1077,
        1068
      ],
      "score": 0.9907228946685791
    },
    {
      "text": "23. Díjole él: ¿Por qué quieres ir á visitarle? hoy no es dia",
      "box": [
        775,
        1045,
        1321,
        1097
      ],
      "score": 0.9875720143318176
    },
    {
      "text": "Eliseo multiplica el aceite de una póbre viuda; alcanza del Señor un hijo",
      "box": [
        18,
        1079,
        602,
        1113
      ],
      "score": 0.991879940032959
    },
    {
      "text": "de Calendas, ni de Sábado. Mas ella respondió: Déjame ir.",
      "box": [
        756,
        1075,
        1287,
        1119
      ],
      "score": 0.9993248581886292
    },
    {
      "text": "á una mujer de Sunam, le resucita despues de muerto, y obra otros",
      "box": [
        36,
        1100,
        604,
        1134
      ],
      "score": 0.9891536831855774
    },
    {
      "text": "24. Hizo pues aparejar la borrica, y dijo al criado: Arrea,",
      "box": [
        774,
        1096,
        1321,
        1144
      ],
      "score": 0.9985870718955994
    },
    {
      "text": "milagros 3.",
      "box": [
        37,
        1130,
        140,
        1156
      ],
      "score": 0.9323678612709045
    },
    {
      "text": "y dáte priesa, no me hagas detener en el camino; y haz esto",
      "box": [
        754,
        1120,
        1322,
        1168
      ],
      "score": 0.9975619316101074
    },
    {
      "text": "1. Vino á aclamar á Eliséo la mujer de uno de los profe-",
      "box": [
        40,
        1161,
        605,
        1199
      ],
      "score": 0.9858707189559937
    },
    {
      "text": "que te mando.",
      "box": [
        758,
        1159,
        891,
        1189
      ],
      "score": 0.9998480081558228
    },
    {
      "text": "25. Partió pués, y fué á encontrar al varon de Dios en el",
      "box": [
        775,
        1168,
        1323,
        1215
      ],
      "score": 0.9886681437492371
    },
    {
      "text": "tas 4, diciendo: Mi marido, siervo tuyo, ha muerto; y bien",
      "box": [
        19,
        1186,
        606,
        1225
      ],
      "score": 0.9927099347114563
    },
    {
      "text": "monte Carmelo; quien al verla venir hácia él, dijo á Giezi su",
      "box": [
        756,
        1193,
        1323,
        1241
      ],
      "score": 0.9994717240333557
    },
    {
      "text": "sabes que tu siervo era temeroso de Dios. Pero ahora viene",
      "box": [
        20,
        1210,
        606,
        1250
      ],
      "score": 0.9996567368507385
    },
    {
      "text": "criado: Mira, aquella es la Sunamitis:",
      "box": [
        759,
        1228,
        1100,
        1260
      ],
      "score": 0.9999172687530518
    },
    {
      "text": "su acreedor para llevarse mis dos hijos y hacerlos esclavos",
      "box": [
        21,
        1236,
        607,
        1275
      ],
      "score": 0.9975613951683044
    },
    {
      "text": "26. Sal á su encuentro, y díle: ¿Lo pasais bien tú, tu mari-",
      "box": [
        777,
        1244,
        1323,
        1286
      ],
      "score": 0.9906902313232422
    },
    {
      "text": "suyos.",
      "box": [
        22,
        1273,
        96,
        1300
      ],
      "score": 0.999576985836029
    },
    {
      "text": "do y tu hijo? Bien, respondió ella.",
      "box": [
        759,
        1277,
        1064,
        1308
      ],
      "score": 0.9968405365943909
    },
    {
      "text": "2. Díjola Eliséo: ¿Qué quieres que yo haga por tí? Díme:",
      "box": [
        46,
        1285,
        608,
        1323
      ],
      "score": 0.988714873790741
    },
    {
      "text": "27. Mas así que llegó al monte y á la presencia del varon",
      "box": [
        778,
        1293,
        1324,
        1335
      ],
      "score": 0.9966022968292236
    },
    {
      "text": "¿qué tienes en tu casa? Ella respondió: No tiene tu esclava otra",
      "box": [
        26,
        1309,
        609,
        1350
      ],
      "score": 0.9970054030418396
    },
    {
      "text": "de Dios, se echó á sus piés, y acercándose Giezi para apartar-",
      "box": [
        759,
        1317,
        1325,
        1359
      ],
      "score": 0.9875628352165222
    },
    {
      "text": "cosa en su casa, sino un poco de aceite para ungirse.",
      "box": [
        29,
        1338,
        537,
        1373
      ],
      "score": 0.9868537187576294
    },
    {
      "text": "la, díjole el varon de Dios: Déjala; porque su alma está llena",
      "box": [
        758,
        1341,
        1326,
        1384
      ],
      "score": 0.9947187900543213
    },
    {
      "text": "3. A la cual dijo: Anda y pide prestadas á todos tus veci-",
      "box": [
        53,
        1362,
        609,
        1396
      ],
      "score": 0.988018810749054
    },
    {
      "text": "de amargura, y el Señor me lo ha ocultado, y no me ha reve-",
      "box": [
        759,
        1366,
        1326,
        1408
      ],
      "score": 0.991595447063446
    },
    {
      "text": "nos vasijas vacías en abundancia:",
      "box": [
        32,
        1391,
        354,
        1423
      ],
      "score": 0.9885789155960083
    },
    {
      "text": "lado nada de eso.",
      "box": [
        760,
        1399,
        920,
        1429
      ],
      "score": 0.9983553290367126
    },
    {
      "text": "4. Entra despues en tu casa, y cierra la puerta, en estando",
      "box": [
        55,
        1409,
        610,
        1447
      ],
      "score": 0.9949562549591064
    },
    {
      "text": "28. Dijo entonces ella: ¿Por ventura, oh señor mio, te pedí",
      "box": [
        779,
        1410,
        1327,
        1456
      ],
      "score": 0.9902841448783875
    },
    {
      "text": "dentro tú y tus hijos; y echa de aquel aceite en todas estas",
      "box": [
        34,
        1433,
        612,
        1474
      ],
      "score": 0.9919958710670471
    },
    {
      "text": "yo un hijo? ¿No te dije que no me engañaras?",
      "box": [
        761,
        1442,
        1178,
        1479
      ],
      "score": 0.9980048537254333
    },
    {
      "text": "vasijas, y cuando estuvieren llenas las pondrás aparte.",
      "box": [
        34,
        1459,
        542,
        1501
      ],
      "score": 0.9999448657035828
    },
    {
      "text": "29. Y él dijo á Giezi: Pon haldas en cinta, y toma en tu",
      "box": [
        780,
        1460,
        1328,
        1504
      ],
      "score": 0.9823487401008606
    },
    {
      "text": "5. Fuése pues la mujer, y cerróse en casa con sus hijos:",
      "box": [
        60,
        1483,
        612,
        1523
      ],
      "score": 0.99578458070755
    },
    {
      "text": "mano.mi báculo, y marcha: si te encontraras con alguno, no",
      "box": [
        761,
        1487,
        1329,
        1526
      ],
      "score": 0.9844254851341248
    },
    {
      "text": "presentábanle estos las vasijas, y ella las llenaba.",
      "box": [
        37,
        1509,
        496,
        1550
      ],
      "score": 0.9881910085678101
    },
    {
      "text": "te pares á saludarle: si alguno te saludare, no te detengas á",
      "box": [
        761,
        1510,
        1330,
        1551
      ],
      "score": 0.9889453053474426
    },
    {
      "text": "6. Llenas ya las vasijas, dijo á uno de los hijos: Tráeme",
      "box": [
        62,
        1531,
        612,
        1572
      ],
      "score": 0.9996798038482666
    },
    {
      "text": "responderle; y pondrás mi báculo sobre el rostro del niño.",
      "box": [
        762,
        1537,
        1295,
        1572
      ],
      "score": 0.9911792278289795
    },
    {
      "text": "todavía otra vasija; y respondió él: No tengo mas. Entonces",
      "box": [
        40,
        1555,
        614,
        1597
      ],
      "score": 0.9963617324829102
    },
    {
      "text": "30.. Sin embargo la madre del niño dijo á Eliséo: Júrote",
      "box": [
        782,
        1558,
        1330,
        1597
      ],
      "score": 0.9956483840942383
    },
    {
      "text": "cesó de multiplicarse el aceite.",
      "box": [
        43,
        1588,
        342,
        1622
      ],
      "score": 0.9937949180603027
    },
    {
      "text": "por el Señor y por tu vida que no me iré sin tí. Con esto se",
      "box": [
        762,
        1581,
        1331,
        1623
      ],
      "score": 0.9945915341377258
    },
    {
      "text": "7.  Fué luego ella, y se lo contó todo al varon de Dios, el",
      "box": [
        64,
        1604,
        614,
        1647
      ],
      "score": 0.985869824886322
    },
    {
      "text": "puso Eliséo en camino, y la fué siguiendo.",
      "box": [
        763,
        1610,
        1148,
        1647
      ],
      "score": 0.9991387128829956
    },
    {
      "text": "cual dijo: Anda, vende el aceite, y paga á tu acreedor; y de lo",
      "box": [
        45,
        1629,
        614,
        1673
      ],
      "score": 0.9936841130256653
    },
    {
      "text": "31. Entre tanto Giezi habia ido delante de ellos, y puesto el",
      "box": [
        781,
        1628,
        1333,
        1671
      ],
      "score": 0.9837350845336914
    },
    {
      "text": "restante sustentaos tú y tus hijos.",
      "box": [
        45,
        1661,
        361,
        1696
      ],
      "score": 0.9994537234306335
    },
    {
      "text": "báculo sobre la cara del niño, el cual ni hablaba ni sentia. Y",
      "box": [
        763,
        1651,
        1332,
        1694
      ],
      "score": 0.9990012049674988
    },
    {
      "text": "8. Pasaba un dia Eliséo por la ciudad de Sunam, y habia",
      "box": [
        67,
        1677,
        614,
        1720
      ],
      "score": 0.9988322854042053
    },
    {
      "text": "así volvió en busca de Eliséo, y dióle parte, diciendo: El niño",
      "box": [
        762,
        1675,
        1332,
        1719
      ],
      "score": 0.9964055418968201
    },
    {
      "text": "en ella una señora de gran consideracion, que le detuvo á co-",
      "box": [
        47,
        1704,
        614,
        1744
      ],
      "score": 0.9987348318099976
    },
    {
      "text": "no ha resucitado.",
      "box": [
        762,
        1712,
        924,
        1743
      ],
      "score": 0.9999361634254456
    },
    {
      "text": "mer; y como pasase por allí frecuentemente, se detenia á comer",
      "box": [
        47,
        1728,
        614,
        1768
      ],
      "score": 0.9953548312187195
    },
    {
      "text": "32. Entró pues Eliséo en la casa, y halló al niño muerto, y",
      "box": [
        782,
        1723,
        1332,
        1766
      ],
      "score": 0.9952443838119507
    },
    {
      "text": "en dicha casa.",
      "box": [
        50,
        1765,
        186,
        1790
      ],
      "score": 0.9801374077796936
    },
    {
      "text": "tendido sobre su cama.",
      "box": [
        763,
        1758,
        975,
        1790
      ],
      "score": 0.9998884797096252
    },
    {
      "text": "9. Y dijo la señora á su marido: Advierto que este hombre",
      "box": [
        70,
        1775,
        614,
        1815
      ],
      "score": 0.9996491074562073
    },
    {
      "text": "33: Entrado que hubo, cerróse dentro con el niño, é hizo",
      "box": [
        782,
        1768,
        1332,
        1815
      ],
      "score": 0.9848294258117676
    },
    {
      "text": "que pasa con frecuencia por nuestra casa, es un varon santo",
      "box": [
        50,
        1799,
        615,
        1842
      ],
      "score": 0.9963394999504089
    },
    {
      "text": "oracion al Señor.",
      "box": [
        763,
        1808,
        918,
        1839
      ],
      "score": 0.9847338199615479
    },
    {
      "text": "de Dios.",
      "box": [
        50,
        1837,
        136,
        1865
      ],
      "score": 0.9994533061981201
    },
    {
      "text": "4 Véase Profeta.",
      "box": [
        781,
        1873,
        918,
        1901
      ],
      "score": 0.9665476083755493
    },
    {
      "text": "1 Esto es, por los que arrojaban con máquinas piedras muy grandes.",
      "box": [
        69,
        1890,
        599,
        1930
      ],
      "score": 0.9993876814842224
    },
    {
      "text": "5 Véase Uncion.",
      "box": [
        783,
        1895,
        916,
        1922
      ],
      "score": 0.9878292083740234
    },
    {
      "text": "2. A Moloch su dios, para aplacarle con este horrendo sacrificio de lo",
      "box": [
        71,
        1912,
        616,
        1950
      ],
      "score": 0.9873836040496826
    },
    {
      "text": "6 Paróse ante el aposento de Eliséo.",
      "box": [
        783,
        1905,
        1065,
        1945
      ],
      "score": 0.9841892719268799
    },
    {
      "text": "que mas amaba.",
      "box": [
        53,
        1943,
        190,
        1976
      ],
      "score": 0.9852579236030579
    },
    {
      "text": "3 Año del MuNDo 3109: antes de JEsU-CHRISto 895.",
      "box": [
        69,
        1955,
        483,
        1994
      ],
      "score": 0.9251578450202942
    }
  ]
}