{
  "volume": 3,
  "page_index": 390,
  "pdf_page": 391,
  "lines": [
    {
      "text": "LA PROFECÍA DE MALACHIAS",
      "box": [
        52,
        60,
        856,
        154
      ],
      "score": 0.9942644238471985
    },
    {
      "text": "ADVERTENCIA",
      "box": [
        378,
        282,
        533,
        304
      ],
      "score": 0.9998564124107361
    },
    {
      "text": "debe entenderse el Bautista, segun lo que se dice en los Evangelios",
      "box": [
        16,
        427,
        397,
        460
      ],
      "score": 0.8686823844909668
    },
    {
      "text": "CAPITULO PRIMERO",
      "box": [
        144,
        574,
        286,
        588
      ],
      "score": 0.9998223185539246
    },
    {
      "text": "despues decís: ¿En qué te hemos ultrajado? En eso que decís:",
      "box": [
        505,
        555,
        882,
        586
      ],
      "score": 0.9980117082595825
    },
    {
      "text": "La mesa del Señor está envilecida.",
      "box": [
        503,
        578,
        715,
        600
      ],
      "score": 0.9989616274833679
    },
    {
      "text": "El Señor reprende á los hijos de Israél por su ingratitud: se lamenta de",
      "box": [
        1,
        599,
        406,
        625
      ],
      "score": 0.9543511271476746
    },
    {
      "text": "8. Si ofreciereis una res ciega para ser inmolada, ¿no será",
      "box": [
        515,
        588,
        883,
        616
      ],
      "score": 0.9844136238098145
    },
    {
      "text": "que los sacerdotes no le dan el culto que le deben; y anuncia que ven-",
      "box": [
        14,
        616,
        405,
        637
      ],
      "score": 0.9850606918334961
    },
    {
      "text": "esto una cosa mal hecha? Y si ofreciereis una res coja y en-",
      "box": [
        503,
        605,
        884,
        631
      ],
      "score": 0.9977160096168518
    },
    {
      "text": "drá dia en que se le ofrecerá en todo lugar una oblacion pura, y será",
      "box": [
        14,
        631,
        405,
        651
      ],
      "score": 0.9628683924674988
    },
    {
      "text": "ferma, ¿no será esto una cosa mala? Preséntasela á tu caudillo,",
      "box": [
        503,
        621,
        883,
        647
      ],
      "score": 0.9971997141838074
    },
    {
      "text": "venerado su Nombre.",
      "box": [
        15,
        649,
        150,
        663
      ],
      "score": 0.9996851682662964
    },
    {
      "text": "y verás si le será grata, y si te recibirá benignamente, dice",
      "box": [
        503,
        637,
        884,
        664
      ],
      "score": 0.984463632106781
    },
    {
      "text": "el Señor de los ejércitos.",
      "box": [
        503,
        660,
        654,
        679
      ],
      "score": 0.9969049692153931
    },
    {
      "text": "1. Duro anuncio del Señor contra Israél por medio de",
      "box": [
        12,
        681,
        403,
        706
      ],
      "score": 0.990083634853363
    },
    {
      "text": "9. Ahora pues orad en la presencia de Dios, para que se",
      "box": [
        515,
        670,
        885,
        695
      ],
      "score": 0.9913476705551147
    },
    {
      "text": "apiade de vosotros (porque tales han sido vuestros proce-",
      "box": [
        503,
        686,
        887,
        711
      ],
      "score": 0.9996338486671448
    },
    {
      "text": "Malachias.",
      "box": [
        0,
        704,
        81,
        721
      ],
      "score": 0.9996966123580933
    },
    {
      "text": "2. Yo os amé, dice el Señor, y vosotros habeis dicho: ¿En",
      "box": [
        10,
        713,
        401,
        740
      ],
      "score": 0.9907537698745728
    },
    {
      "text": "deres): quizá él os acogerá benignamente, dice el Señor de",
      "box": [
        503,
        702,
        886,
        728
      ],
      "score": 0.9926748871803284
    },
    {
      "text": "los ejércitos.",
      "box": [
        501,
        725,
        582,
        744
      ],
      "score": 0.9955592155456543
    },
    {
      "text": "qué nos amaste? Pues qué, dice el Señor, ¿no era Esaú her-",
      "box": [
        0,
        730,
        401,
        756
      ],
      "score": 0.9863229990005493
    },
    {
      "text": "10. ¿Quién hay entre vosotros que cierre de balde las",
      "box": [
        515,
        735,
        887,
        759
      ],
      "score": 0.999810516834259
    },
    {
      "text": "mano de Jacob, y yo amé mas á Jacob,",
      "box": [
        0,
        749,
        269,
        772
      ],
      "score": 0.9844536185264587
    },
    {
      "text": "puertas, y encienda el fuego sobre mi altar 7? El afecto mio",
      "box": [
        501,
        752,
        888,
        776
      ],
      "score": 0.9882002472877502
    },
    {
      "text": "3. Y aborrecí ó amé menos á Esaú ³, y reduje á soledad",
      "box": [
        9,
        762,
        400,
        788
      ],
      "score": 0.9349711537361145
    },
    {
      "text": "no es hácia vosotros, dice el Señor de los ejércitos; ni acep-",
      "box": [
        502,
        769,
        888,
        791
      ],
      "score": 0.9875797033309937
    },
    {
      "text": "sus montañas, abandonando su heredad á los dragones del",
      "box": [
        0,
        778,
        401,
        806
      ],
      "score": 0.9992884993553162
    },
    {
      "text": "taré de vuestra mano ofrenda ninguna.",
      "box": [
        501,
        788,
        747,
        808
      ],
      "score": 0.9913923740386963
    },
    {
      "text": "lesierto?",
      "box": [
        0,
        802,
        67,
        821
      ],
      "score": 0.9985461831092834
    },
    {
      "text": "11. Porque desde Levante á Poniente es grande mi Nom-",
      "box": [
        513,
        800,
        890,
        826
      ],
      "score": 0.9985753297805786
    },
    {
      "text": "4. Que si los Iduméos dijeren: Destruidos hemos sido,",
      "box": [
        6,
        811,
        399,
        838
      ],
      "score": 0.9995777010917664
    },
    {
      "text": "bre entre las naciones, y en todo lugar se sacrifica y se",
      "box": [
        501,
        819,
        890,
        842
      ],
      "score": 0.9974612593650818
    },
    {
      "text": "oero volveremos á restaurar nuestras ruinas: hé aquí lo que",
      "box": [
        0,
        828,
        399,
        853
      ],
      "score": 0.9852156043052673
    },
    {
      "text": "lice el Señor de los ejércitos: Ellos edificarán, y yo destruiré;",
      "box": [
        0,
        843,
        400,
        870
      ],
      "score": 0.9916070699691772
    },
    {
      "text": "ofrece al Nombre mio una ofrenda pura®; pues grande es",
      "box": [
        501,
        836,
        890,
        858
      ],
      "score": 0.990399181842804
    },
    {
      "text": " serán llamados país impío, pueblo contra el cual está el",
      "box": [
        0,
        859,
        400,
        886
      ],
      "score": 0.9779288172721863
    },
    {
      "text": "mi Nombre entre las naciones 9, dice el Señor de los ejér-",
      "box": [
        499,
        852,
        890,
        875
      ],
      "score": 0.9910784959793091
    },
    {
      "text": "Señor indignado para siempre.",
      "box": [
        0,
        879,
        209,
        901
      ],
      "score": 0.995771586894989
    },
    {
      "text": "citos.",
      "box": [
        499,
        875,
        537,
        893
      ],
      "score": 0.9988806843757629
    },
    {
      "text": "5. Vosotros vereis esto con vuestros ojos, y direis: Glori-",
      "box": [
        7,
        892,
        399,
        917
      ],
      "score": 0.9817644357681274
    },
    {
      "text": "12. Pero vosotros le habeis profanado, diciendo: La mesa",
      "box": [
        512,
        886,
        891,
        908
      ],
      "score": 0.9990994334220886
    },
    {
      "text": "icado sea el Señor mas allá de los confines de Israél .",
      "box": [
        0,
        908,
        351,
        934
      ],
      "score": 0.9828579425811768
    },
    {
      "text": "del Señor está contaminada, y es cosa vil lo que se ofrece",
      "box": [
        499,
        903,
        892,
        925
      ],
      "score": 0.999548614025116
    },
    {
      "text": "6. Honra á su padre el hijo, y el siervo honra á su señor:",
      "box": [
        7,
        925,
        398,
        950
      ],
      "score": 0.9840953350067139
    },
    {
      "text": "sobre ella, juntamente con el fuego que lo consume.",
      "box": [
        498,
        921,
        832,
        942
      ],
      "score": 0.9997007846832275
    },
    {
      "text": "pues si yo soy vuestro Padre, ¿dónde está la honra que me",
      "box": [
        0,
        941,
        397,
        967
      ],
      "score": 0.9965056777000427
    },
    {
      "text": "13. Y vosotros decís: Hé aquí el fruto de nuestro trabajo,",
      "box": [
        511,
        938,
        893,
        958
      ],
      "score": 0.9901598691940308
    },
    {
      "text": "corresponde? Y si yo soy vuestro Señor, ¿dónde está la re-",
      "box": [
        0,
        958,
        397,
        983
      ],
      "score": 0.9790285229682922
    },
    {
      "text": "y le envileceis, dice el Señor de los ejércitos, y ofreceis la",
      "box": [
        498,
        955,
        894,
        975
      ],
      "score": 0.9996384978294373
    },
    {
      "text": "rerencia que me es debida? dice el Señor de los ejércitos á",
      "box": [
        0,
        975,
        397,
        1000
      ],
      "score": 0.9870215058326721
    },
    {
      "text": "res coja y enferma, y me presentais una ofrenda de lo que",
      "box": [
        498,
        972,
        893,
        991
      ],
      "score": 0.9994574189186096
    },
    {
      "text": "rosotros, Ios sacerdotes que despreciais mi Nombre, y decís:",
      "box": [
        0,
        993,
        394,
        1014
      ],
      "score": 0.9858453273773193
    },
    {
      "text": "habeis robado. Pues qué, ¿he de aceptarla yo de vuestra",
      "box": [
        498,
        989,
        894,
        1007
      ],
      "score": 0.9869635701179504
    },
    {
      "text": "En qué hemos despreciado tu Nombre 5?",
      "box": [
        0,
        1010,
        271,
        1031
      ],
      "score": 0.9621948003768921
    },
    {
      "text": "mano, dice el Señor?",
      "box": [
        497,
        1005,
        630,
        1024
      ],
      "score": 0.9988569021224976
    },
    {
      "text": "7.  Vosotros ofreceis sobre mi altar un pan impuro; y",
      "box": [
        6,
        1026,
        394,
        1048
      ],
      "score": 0.9718249440193176
    },
    {
      "text": "14. Maldito será el hombre fraudulento, el cual tiene en",
      "box": [
        509,
        1021,
        894,
        1040
      ],
      "score": 0.9980379939079285
    },
    {
      "text": "1 Cap. II, v. 8.",
      "box": [
        5,
        1065,
        106,
        1086
      ],
      "score": 0.9533143639564514
    },
    {
      "text": "nistros, y á todos los fieles; Mancillamos, dicc, el pan, esto es, el cuerpo",
      "box": [
        495,
        1062,
        895,
        1080
      ],
      "score": 0.9889737367630005
    },
    {
      "text": "Luc. I, v. 17 y 78.—Joan. I, v. 21.—Matth. X1, v. 14.—XV1I, v. 12.",
      "box": [
        18,
        1078,
        392,
        1099
      ],
      "score": 0.9212981462478638
    },
    {
      "text": "de Christo, cuando nos acercamos indignamente al altar, y estando sucios",
      "box": [
        495,
        1077,
        895,
        1093
      ],
      "score": 0.9911314845085144
    },
    {
      "text": "Ingrato el pueblo de Israél á tantos bencficios recibidos de Dios, ni",
      "box": [
        18,
        1092,
        394,
        1114
      ],
      "score": 0.9273394346237183
    },
    {
      "text": "bebemos aquella sangre limpia; y dccimos: La mesa del Señor está envi-",
      "box": [
        496,
        1093,
        893,
        1107
      ],
      "score": 0.9850839972496033
    },
    {
      "text": "lecida. Es verdad que nadie se atreve á hablar asi,y á expresar con pala-",
      "box": [
        496,
        1107,
        893,
        1121
      ],
      "score": 0.9773949384689331
    },
    {
      "text": "bras tan impão pensamiento; mas las obras de los pecadores son un des-",
      "box": [
        495,
        1121,
        893,
        1135
      ],
      "score": 0.9910482168197632
    },
    {
      "text": "precio de la mesa del Señor; pues éste es vilipendiadoy ultrajado, cuando",
      "box": [
        494,
        1136,
        892,
        1150
      ],
      "score": 0.9955904483795166
    },
    {
      "text": "racion.",
      "box": [
        0,
        1152,
        46,
        1166
      ],
      "score": 0.9851999878883362
    },
    {
      "text": "lo son sus sacramentos.",
      "box": [
        494,
        1150,
        616,
        1163
      ],
      "score": 0.9986541867256165
    },
    {
      "text": "r Todos recibís vuestro estipendio: pues os manteneis con las obla-",
      "box": [
        502,
        1161,
        892,
        1179
      ],
      "score": 0.9799285531044006
    },
    {
      "text": "ciones, las víctimas, las primicias, ete.",
      "box": [
        495,
        1177,
        703,
        1191
      ],
      "score": 0.9828209280967712
    },
    {
      "text": "honra que me debsis? Y si",
      "box": [
        0,
        1188,
        152,
        1209
      ],
      "score": 0.9655187726020813
    },
    {
      "text": "vuestro Señor, ¿qué es del temor que me",
      "box": [
        178,
        1189,
        392,
        1212
      ],
      "score": 0.9719579815864563
    },
    {
      "text": "8 Estas palabras de Malachias demuestran bien que en la nueva Ley",
      "box": [
        502,
        1189,
        892,
        1209
      ],
      "score": 0.9858331680297852
    },
    {
      "text": "teneis? etc.",
      "box": [
        0,
        1206,
        64,
        1222
      ],
      "score": 0.9593817591667175
    },
    {
      "text": "se ofrece un verdadero y propio sacrificio, sustituido por Dios á los",
      "box": [
        491,
        1204,
        892,
        1224
      ],
      "score": 0.9891653656959534
    },
    {
      "text": "sacrificios de la antigua Ley; y así sacrificio exterior, el cual (como en",
      "box": [
        492,
        1218,
        892,
        1239
      ],
      "score": 0.9922557473182678
    },
    {
      "text": "eon las carnes que me ofreceis",
      "box": [
        0,
        1230,
        173,
        1252
      ],
      "score": 0.9685526490211487
    },
    {
      "text": " como en un convite, dice Dios, con la flor",
      "box": [
        164,
        1230,
        391,
        1254
      ],
      "score": 0.9772128462791443
    },
    {
      "text": "la antigua Ley) debe siempre ir acompañado del sacrificio interior del",
      "box": [
        491,
        1233,
        892,
        1253
      ],
      "score": 0.9942967295646667
    },
    {
      "text": "corazon. Nótese que la palabra hebrea, que la Vulgata traduce oblatio, sig-",
      "box": [
        492,
        1247,
        891,
        1268
      ],
      "score": 0.9832085967063904
    },
    {
      "text": "nifca la ofrenda de pan, la de harina, la de grano, y la de vino. Hebr. VII.",
      "box": [
        490,
        1260,
        892,
        1285
      ],
      "score": 0.8020082116127014
    },
    {
      "text": "aplica San Gerónimo á los prelados de la Iglesia, y á los sacerdotes y mi-",
      "box": [
        0,
        1274,
        391,
        1299
      ],
      "score": 0.8387648463249207
    },
    {
      "text": "9 Psalm. CXII, v. 3.",
      "box": [
        502,
        1274,
        623,
        1294
      ],
      "score": 0.9038031697273254
    }
  ]
}